[
    {
        "date": "2020-12-30T00:00:00+07:00",
        "period": "2020",
        "symbol": "BCH",
        "market": "SET",
        "industry": "SERVICE",
        "sector": "HELTH",
        "prior": 17.1,
        "open": 17.1,
        "high": 17.2,
        "low": 10.0,
        "average": null,
        "close": 13.6,
        "change": -3.5000000000000018,
        "percentChange": -20.46783625730995,
        "totalVolume": 2393246999.0,
        "totalValue": 34137326346.300007,
        "pe": 28.45,
        "pbv": 5.12,
        "bookValuePerShare": 2.66,
        "dividendYield": 1.690000057220459,
        "marketCap": 33914972582.4,
        "listedShare": 2493747984.0,
        "par": 1.0,
        "financialDate": "2020-09-30T00:00:00+07:00",
        "turnoverRatio": 95.96988205525102,
        "beta": 1.0,
        "dividendPayoutRatio": 0.48,
        "averageValue": 140482824.4703704
    },
    {
        "date": "2021-12-30T00:00:00+07:00",
        "period": "2021",
        "symbol": "BCH",
        "market": "SET",
        "industry": "SERVICE",
        "sector": "HELTH",
        "prior": 13.6,
        "open": 13.5,
        "high": 26.75,
        "low": 13.3,
        "average": null,
        "close": 20.1,
        "change": 6.500000000000002,
        "percentChange": 47.79411764705884,
        "totalVolume": 5845996025.0,
        "totalValue": 118078788168.55,
        "pe": 10.79,
        "pbv": 4.75,
        "bookValuePerShare": 4.23,
        "dividendYield": 1.1399999856948853,
        "marketCap": 50124334478.4,
        "listedShare": 2493747984.0,
        "par": 1.0,
        "financialDate": "2021-09-30T00:00:00+07:00",
        "turnoverRatio": 234.42609527940175,
        "beta": -0.1,
        "dividendPayoutRatio": 0.18,
        "averageValue": 489953477.8778008
    },
    {
        "date": "2022-12-30T00:00:00+07:00",
        "period": "2022",
        "symbol": "BCH",
        "market": "SET",
        "industry": "SERVICE",
        "sector": "HELTH",
        "prior": 20.1,
        "open": 19.9,
        "high": 23.1,
        "low": 16.8,
        "average": null,
        "close": 20.5,
        "change": 0.3999999999999986,
        "percentChange": 1.9900497512437738,
        "totalVolume": 4604238628.0,
        "totalValue": 90655374843.84,
        "pe": 9.74,
        "pbv": 4.19,
        "bookValuePerShare": 4.89,
        "dividendYield": 5.849999904632568,
        "marketCap": 51121833672.0,
        "listedShare": 2493747984.0,
        "par": 1.0,
        "financialDate": "2022-09-30T00:00:00+07:00",
        "turnoverRatio": 184.63127218712572,
        "beta": 0.24,
        "dividendPayoutRatio": 0.67,
        "averageValue": 376163381.09477174
    },
    {
        "date": "2023-12-28T00:00:00+07:00",
        "period": "2023",
        "symbol": "BCH",
        "market": "SET",
        "industry": "SERVICE",
        "sector": "HELTH",
        "prior": 20.5,
        "open": 20.6,
        "high": 22.6,
        "low": 16.6,
        "average": null,
        "close": 22.4,
        "change": 1.8999999999999986,
        "percentChange": 9.268292682926822,
        "totalVolume": 2660692044.0,
        "totalValue": 52498960968.36,
        "pe": 44.74,
        "pbv": 4.59,
        "bookValuePerShare": 4.88,
        "dividendYield": 3.569999933242798,
        "marketCap": 55859954841.6,
        "listedShare": 2493747984.0,
        "par": 1.0,
        "financialDate": "2023-09-30T00:00:00+07:00",
        "turnoverRatio": 106.69450405859456,
        "beta": 0.66,
        "dividendPayoutRatio": 1.0,
        "averageValue": 216045106.86567903
    },
    {
        "date": "2024-02-23T00:00:00+07:00",
        "period": "YTD",
        "symbol": "BCH",
        "market": "SET",
        "industry": "SERVICE",
        "sector": "HELTH",
        "prior": 22.4,
        "open": 22.6,
        "high": 23.8,
        "low": 21.5,
        "average": null,
        "close": 21.6,
        "change": -0.7999999999999972,
        "percentChange": -3.571428571428559,
        "totalVolume": 501824890.0,
        "totalValue": 11246731363.300001,
        "pe": 43.14,
        "pbv": 4.42,
        "bookValuePerShare": 4.88,
        "dividendYield": 3.700000047683716,
        "marketCap": 53864956454.4,
        "listedShare": 2493747984.0,
        "par": 1.0,
        "financialDate": "2023-09-30T00:00:00+07:00",
        "turnoverRatio": 20.123320127764764,
        "beta": 0.65,
        "dividendPayoutRatio": 1.0,
        "averageValue": 288377727.2641026
    }
]