[
    {
        "date": "2020-12-30T00:00:00+07:00",
        "period": "2020",
        "symbol": "VGI",
        "market": "SET",
        "industry": "SERVICE",
        "sector": "MEDIA",
        "prior": 9.55,
        "open": 9.6,
        "high": 9.9,
        "low": 4.86,
        "average": null,
        "close": 6.65,
        "change": -2.9000000000000004,
        "percentChange": -30.366492146596862,
        "totalVolume": 9197822103.0,
        "totalValue": 64501748749.479996,
        "pe": 85.14,
        "pbv": 3.96,
        "bookValuePerShare": 1.68,
        "dividendYield": 0.9200000166893005,
        "marketCap": 57264251958.2,
        "listedShare": 8611165708.0,
        "par": 0.1,
        "financialDate": "2020-09-30T00:00:00+07:00",
        "turnoverRatio": 106.8127407596292,
        "beta": 1.29,
        "dividendPayoutRatio": 0.78,
        "averageValue": 265439295.26534978
    },
    {
        "date": "2021-12-30T00:00:00+07:00",
        "period": "2021",
        "symbol": "VGI",
        "market": "SET",
        "industry": "SERVICE",
        "sector": "MEDIA",
        "prior": 6.65,
        "open": 6.35,
        "high": 7.6,
        "low": 5.45,
        "average": null,
        "close": 6.6,
        "change": -0.05000000000000071,
        "percentChange": -0.7518796992481309,
        "totalVolume": 7576279562.0,
        "totalValue": 49857087970.98,
        "pe": 52.99,
        "pbv": 3.68,
        "bookValuePerShare": 1.8,
        "dividendYield": 0.9200000166893005,
        "marketCap": 56833693672.8,
        "listedShare": 8611165708.0,
        "par": 0.1,
        "financialDate": "2021-09-30T00:00:00+07:00",
        "turnoverRatio": 87.98204353402974,
        "beta": 1.37,
        "dividendPayoutRatio": 0.49,
        "averageValue": 206875883.69701245
    },
    {
        "date": "2022-12-30T00:00:00+07:00",
        "period": "2022",
        "symbol": "VGI",
        "market": "SET",
        "industry": "SERVICE",
        "sector": "MEDIA",
        "prior": 6.6,
        "open": 6.65,
        "high": 6.9,
        "low": 3.46,
        "average": null,
        "close": 4.4,
        "change": -2.1999999999999993,
        "percentChange": -33.33333333333333,
        "totalVolume": 7216252641.0,
        "totalValue": 34626812465.96001,
        "pe": null,
        "pbv": 1.77,
        "bookValuePerShare": 2.48,
        "dividendYield": 0.800000011920929,
        "marketCap": 49255879930.4,
        "listedShare": 11194518166.0,
        "par": 0.1,
        "financialDate": "2022-09-30T00:00:00+07:00",
        "turnoverRatio": 69.02278408293698,
        "beta": 1.18,
        "dividendPayoutRatio": null,
        "averageValue": 143679719.77576765
    },
    {
        "date": "2023-12-28T00:00:00+07:00",
        "period": "2023",
        "symbol": "VGI",
        "market": "SET",
        "industry": "SERVICE",
        "sector": "MEDIA",
        "prior": 4.4,
        "open": 4.4,
        "high": 5.1,
        "low": 1.77,
        "average": null,
        "close": 1.93,
        "change": -2.4700000000000006,
        "percentChange": -56.13636363636365,
        "totalVolume": 7051158981.0,
        "totalValue": 23401589337.520004,
        "pe": null,
        "pbv": 0.79,
        "bookValuePerShare": 2.43,
        "dividendYield": 4.150000095367432,
        "marketCap": 21605422955.38,
        "listedShare": 11194519666.0,
        "par": 0.1,
        "financialDate": "2023-09-30T00:00:00+07:00",
        "turnoverRatio": 62.987604374957684,
        "beta": 1.68,
        "dividendPayoutRatio": null,
        "averageValue": 96302836.77991772
    },
    {
        "date": "2024-02-23T00:00:00+07:00",
        "period": "YTD",
        "symbol": "VGI",
        "market": "SET",
        "industry": "SERVICE",
        "sector": "MEDIA",
        "prior": 1.93,
        "open": 1.94,
        "high": 2.34,
        "low": 1.52,
        "average": null,
        "close": 1.54,
        "change": -0.3899999999999999,
        "percentChange": -20.20725388601036,
        "totalVolume": 3039164365.0,
        "totalValue": 5435930049.15,
        "pe": null,
        "pbv": 0.74,
        "bookValuePerShare": 2.09,
        "dividendYield": 5.190000057220459,
        "marketCap": 17239560285.64,
        "listedShare": 11194519666.0,
        "par": 0.1,
        "financialDate": "2023-12-31T00:00:00+07:00",
        "turnoverRatio": 27.148680387159008,
        "beta": 1.73,
        "dividendPayoutRatio": null,
        "averageValue": 139382821.77307692
    }
]