[
    {
        "symbol": "KKP",
        "quarter": "Q9",
        "year": 2019,
        "fsType": "C",
        "beginDate": "2019-01-01T00:00:00+07:00",
        "endDate": "2019-12-31T00:00:00+07:00",
        "asOfDate": "2019-12-31T00:00:00+07:00",
        "totalAsset": 311690006.0,
        "totalLiability": 267678747.0,
        "equity": 43902105.0,
        "paidupCapital": 8467511.0,
        "totalRevenue": 23778747.0,
        "totalExpense": 18188378.0,
        "sales": null,
        "ebit": 13017182.0,
        "ebitda": 13471977.0,
        "netProfit": 5988444.0,
        "profitFromOtherActivity": 1706851.0,
        "eps": 7.07,
        "netOperating": 325359.0,
        "netInvesting": -5360112.0,
        "netFinancing": 4796088.0,
        "netCashflow": -238665.0,
        "roa": 4.21254731145184,
        "roe": 13.913257064923986,
        "netProfitMargin": 25.18944753480913,
        "grossProfitMargin": null,
        "deRatio": 6.082051572303351,
        "currentRatio": null,
        "quickRatio": null
    },
    {
        "symbol": "KKP",
        "quarter": "Q9",
        "year": 2020,
        "fsType": "C",
        "beginDate": "2020-01-01T00:00:00+07:00",
        "endDate": "2020-12-31T00:00:00+07:00",
        "asOfDate": "2020-12-31T00:00:00+07:00",
        "totalAsset": 363411016.0,
        "totalLiability": 316785295.0,
        "equity": 46517180.0,
        "paidupCapital": 8467511.0,
        "totalRevenue": 25391777.0,
        "totalExpense": 20033414.0,
        "sales": null,
        "ebit": 11391805.0,
        "ebitda": 12002973.0,
        "netProfit": 5123266.0,
        "profitFromOtherActivity": 1128488.0,
        "eps": 6.05,
        "netOperating": 33977004.0,
        "netInvesting": -1329286.0,
        "netFinancing": -32266750.0,
        "netCashflow": 380968.0,
        "roa": 3.3748445428956853,
        "roe": 11.332241788905984,
        "netProfitMargin": 20.25509675829305,
        "grossProfitMargin": null,
        "deRatio": 6.79421761649541,
        "currentRatio": null,
        "quickRatio": null
    },
    {
        "symbol": "KKP",
        "quarter": "Q9",
        "year": 2021,
        "fsType": "C",
        "beginDate": "2021-01-01T00:00:00+07:00",
        "endDate": "2021-12-31T00:00:00+07:00",
        "asOfDate": "2021-12-31T00:00:00+07:00",
        "totalAsset": 436123201.0,
        "totalLiability": 384961046.0,
        "equity": 51046101.0,
        "paidupCapital": 8467511.0,
        "totalRevenue": 29101396.0,
        "totalExpense": 21137069.0,
        "sales": null,
        "ebit": 11585362.0,
        "ebitda": 12278114.0,
        "netProfit": 6318052.0,
        "profitFromOtherActivity": -167398.0,
        "eps": 7.46,
        "netOperating": -20142687.0,
        "netInvesting": 6314887.0,
        "netFinancing": 13579239.0,
        "netCashflow": -248561.0,
        "roa": 2.898027815112258,
        "roe": 12.951700548078124,
        "netProfitMargin": 21.83851592549031,
        "grossProfitMargin": null,
        "deRatio": 7.52433211619018,
        "currentRatio": null,
        "quickRatio": null
    },
    {
        "symbol": "KKP",
        "quarter": "Q9",
        "year": 2022,
        "fsType": "C",
        "beginDate": "2022-01-01T00:00:00+07:00",
        "endDate": "2022-12-31T00:00:00+07:00",
        "asOfDate": "2022-12-31T00:00:00+07:00",
        "totalAsset": 507637018.0,
        "totalLiability": 449525572.0,
        "equity": 57823524.0,
        "paidupCapital": 8467511.0,
        "totalRevenue": 32318482.0,
        "totalExpense": 23655892.0,
        "sales": null,
        "ebit": 14078996.0,
        "ebitda": 14767157.0,
        "netProfit": 7602096.0,
        "profitFromOtherActivity": 827239.0,
        "eps": 8.98,
        "netOperating": -188176.0,
        "netInvesting": -16012591.0,
        "netFinancing": 15958944.0,
        "netCashflow": -241823.0,
        "roa": 2.9835959847762985,
        "roe": 13.96550415232899,
        "netProfitMargin": 23.56682470420486,
        "grossProfitMargin": null,
        "deRatio": 7.735577118490564,
        "currentRatio": null,
        "quickRatio": null
    },
    {
        "symbol": "KKP",
        "quarter": "Q9",
        "year": 2023,
        "fsType": "C",
        "beginDate": "2023-01-01T00:00:00+07:00",
        "endDate": "2023-12-31T00:00:00+07:00",
        "asOfDate": "2023-12-31T00:00:00+07:00",
        "totalAsset": 545327017.0,
        "totalLiability": 484074167.0,
        "equity": 60966939.0,
        "paidupCapital": 8467511.0,
        "totalRevenue": 37741077.0,
        "totalExpense": 31383009.0,
        "sales": null,
        "ebit": 15210251.0,
        "ebitda": 16032629.0,
        "netProfit": 5443403.0,
        "profitFromOtherActivity": 428567.0,
        "eps": 6.43,
        "netOperating": -6900705.0,
        "netInvesting": 3370674.0,
        "netFinancing": 3911385.0,
        "netCashflow": 381354.0,
        "roa": 2.8890352366118566,
        "roe": 9.164713837338946,
        "netProfitMargin": 14.456262072224384,
        "grossProfitMargin": null,
        "deRatio": 7.902883980092355,
        "currentRatio": null,
        "quickRatio": null
    }
]