[
    {
        "symbol": "VGI",
        "quarter": "Q9",
        "year": 2020,
        "fsType": "C",
        "beginDate": "2019-04-01T00:00:00+07:00",
        "endDate": "2020-03-31T00:00:00+07:00",
        "asOfDate": "2020-03-31T00:00:00+07:00",
        "totalAsset": 17076945.8,
        "totalLiability": 3999286.85,
        "equity": 12783895.17,
        "paidupCapital": 861116.57,
        "totalRevenue": 4249759.9,
        "totalExpense": 3251914.02,
        "sales": 3999875.83,
        "ebit": 1176864.83,
        "ebitda": 1796128.79,
        "netProfit": 1423940.1,
        "profitFromOtherActivity": 179018.96,
        "eps": 0.17,
        "netOperating": 997294.7,
        "netInvesting": -275238.55,
        "netFinancing": -1536036.76,
        "netCashflow": -813980.61,
        "roa": 5.919198415608407,
        "roe": 10.754766245767982,
        "netProfitMargin": 30.678549157565346,
        "grossProfitMargin": 51.30564315542765,
        "deRatio": 0.3058106091686999,
        "currentRatio": 0.9800089403280214,
        "quickRatio": 0.8823746351613159
    },
    {
        "symbol": "VGI",
        "quarter": "Q9",
        "year": 2021,
        "fsType": "C",
        "beginDate": "2020-04-01T00:00:00+07:00",
        "endDate": "2021-03-31T00:00:00+07:00",
        "asOfDate": "2021-03-31T00:00:00+07:00",
        "totalAsset": 20970233.97,
        "totalLiability": 3906977.95,
        "equity": 16591691.88,
        "paidupCapital": 861116.57,
        "totalRevenue": 3243852.26,
        "totalExpense": 2469541.56,
        "sales": 3072626.8,
        "ebit": 1112744.74,
        "ebitda": 1582067.89,
        "netProfit": 979765.13,
        "profitFromOtherActivity": 338434.04,
        "eps": 0.11,
        "netOperating": 166187.62,
        "netInvesting": 1303239.72,
        "netFinancing": -738824.56,
        "netCashflow": 730602.79,
        "roa": 5.8492889430134785,
        "roe": 6.670607998395522,
        "netProfitMargin": 27.95061480389369,
        "grossProfitMargin": 49.75333939025722,
        "deRatio": 0.22897024739652838,
        "currentRatio": 1.008505840792053,
        "quickRatio": 0.708480527622276
    },
    {
        "symbol": "VGI",
        "quarter": "Q9",
        "year": 2022,
        "fsType": "C",
        "beginDate": "2021-04-01T00:00:00+07:00",
        "endDate": "2022-03-31T00:00:00+07:00",
        "asOfDate": "2022-03-31T00:00:00+07:00",
        "totalAsset": 40848296.53,
        "totalLiability": 10865586.24,
        "equity": 29133388.58,
        "paidupCapital": 861116.57,
        "totalRevenue": 4426145.09,
        "totalExpense": 4373143.33,
        "sales": 4298449.66,
        "ebit": -141017.37,
        "ebitda": 344792.98,
        "netProfit": -120263.02,
        "profitFromOtherActivity": -194019.14,
        "eps": -0.01,
        "netOperating": -246601.23,
        "netInvesting": -6573246.32,
        "netFinancing": 6553607.84,
        "netCashflow": -266239.71,
        "roa": -0.45623009430804895,
        "roe": -0.5260264991997348,
        "netProfitMargin": -6.235366992906236,
        "grossProfitMargin": 25.34702802591389,
        "deRatio": 0.36239506485255774,
        "currentRatio": 1.6303769270328348,
        "quickRatio": 0.22597866706855974
    },
    {
        "symbol": "VGI",
        "quarter": "Q9",
        "year": 2023,
        "fsType": "C",
        "beginDate": "2022-04-01T00:00:00+07:00",
        "endDate": "2023-03-31T00:00:00+07:00",
        "asOfDate": "2023-03-31T00:00:00+07:00",
        "totalAsset": 33634899.92,
        "totalLiability": 2983452.46,
        "equity": 28128156.22,
        "paidupCapital": 1119451.82,
        "totalRevenue": 5774478.05,
        "totalExpense": 5559942.45,
        "sales": 5564554.1,
        "ebit": -223643.66,
        "ebitda": 292618.65,
        "netProfit": -64881.76,
        "profitFromOtherActivity": -438179.27,
        "eps": -0.01,
        "netOperating": -74459.16,
        "netInvesting": 457312.19,
        "netFinancing": 4281943.04,
        "netCashflow": 4664796.07,
        "roa": -0.6005211124903971,
        "roe": -0.22661547195981344,
        "netProfitMargin": -8.095773435315076,
        "grossProfitMargin": 36.21475061227277,
        "deRatio": 0.09733479839475914,
        "currentRatio": 4.881130328958646,
        "quickRatio": 4.313009513949289
    },
    {
        "symbol": "VGI",
        "quarter": "9M",
        "year": 2024,
        "fsType": "C",
        "beginDate": "2023-04-01T00:00:00+07:00",
        "endDate": "2023-12-31T00:00:00+07:00",
        "asOfDate": "2023-12-31T00:00:00+07:00",
        "totalAsset": 28453793.0,
        "totalLiability": 3221069.0,
        "equity": 23344379.0,
        "paidupCapital": 1119452.0,
        "totalRevenue": 4262830.0,
        "totalExpense": 7231812.0,
        "sales": 4074554.0,
        "ebit": -3608886.0,
        "ebitda": -3143159.0,
        "netProfit": -3539821.0,
        "profitFromOtherActivity": -639904.0,
        "eps": -0.32,
        "netOperating": -670211.0,
        "netInvesting": 554481.0,
        "netFinancing": -2007618.0,
        "netCashflow": -2123348.0,
        "roa": -12.76995929740161,
        "roe": -14.738043220539755,
        "netProfitMargin": -86.5994656132194,
        "grossProfitMargin": 41.25651543702697,
        "deRatio": 0.12765443001714757,
        "currentRatio": 3.6607134754516215,
        "quickRatio": 2.937468364356272
    }
]