[
    {
        "date": "2020-12-30T00:00:00+07:00",
        "period": "2020",
        "symbol": "WHAUP",
        "market": "SET",
        "industry": "RESOURC",
        "sector": "ENERG",
        "prior": 5.45,
        "open": 5.5,
        "high": 5.8,
        "low": 3.16,
        "average": null,
        "close": 4.2,
        "change": -1.25,
        "percentChange": -22.93577981651376,
        "totalVolume": 1610379528.0,
        "totalValue": 6997229575.74,
        "pe": 16.95,
        "pbv": 1.33,
        "bookValuePerShare": 3.17,
        "dividendYield": 6.010000228881836,
        "marketCap": 16065000000.0,
        "listedShare": 3825000000.0,
        "par": 1.0,
        "financialDate": "2020-09-30T00:00:00+07:00",
        "turnoverRatio": 42.10142556862745,
        "beta": 0.78,
        "dividendPayoutRatio": 1.02,
        "averageValue": 28795183.439259257
    },
    {
        "date": "2021-12-30T00:00:00+07:00",
        "period": "2021",
        "symbol": "WHAUP",
        "market": "SET",
        "industry": "RESOURC",
        "sector": "ENERG",
        "prior": 4.2,
        "open": 4.16,
        "high": 4.94,
        "low": 3.94,
        "average": null,
        "close": 4.08,
        "change": -0.1200000000000001,
        "percentChange": -2.8571428571428594,
        "totalVolume": 1489132606.0,
        "totalValue": 6414673818.72,
        "pe": 18.44,
        "pbv": 1.24,
        "bookValuePerShare": 3.28,
        "dividendYield": 6.190000057220459,
        "marketCap": 15606000000.0,
        "listedShare": 3825000000.0,
        "par": 1.0,
        "financialDate": "2021-09-30T00:00:00+07:00",
        "turnoverRatio": 38.93157139869281,
        "beta": 0.8,
        "dividendPayoutRatio": 1.14,
        "averageValue": 26616903.812116183
    },
    {
        "date": "2022-12-30T00:00:00+07:00",
        "period": "2022",
        "symbol": "WHAUP",
        "market": "SET",
        "industry": "RESOURC",
        "sector": "ENERG",
        "prior": 4.08,
        "open": 4.08,
        "high": 4.22,
        "low": 3.66,
        "average": null,
        "close": 4.1,
        "change": 0.019999999999999574,
        "percentChange": 0.4901960784313621,
        "totalVolume": 821507956.0,
        "totalValue": 3284209706.4,
        "pe": 33.91,
        "pbv": 1.22,
        "bookValuePerShare": 3.35,
        "dividendYield": 6.159999847412109,
        "marketCap": 15682500000.0,
        "listedShare": 3825000000.0,
        "par": 1.0,
        "financialDate": "2022-09-30T00:00:00+07:00",
        "turnoverRatio": 21.477332183006535,
        "beta": 0.6,
        "dividendPayoutRatio": 1.82,
        "averageValue": 13627426.167634856
    },
    {
        "date": "2023-12-28T00:00:00+07:00",
        "period": "2023",
        "symbol": "WHAUP",
        "market": "SET",
        "industry": "RESOURC",
        "sector": "ENERG",
        "prior": 4.1,
        "open": 4.1,
        "high": 4.34,
        "low": 3.48,
        "average": null,
        "close": 3.94,
        "change": -0.1599999999999997,
        "percentChange": -3.9024390243902367,
        "totalVolume": 582270372.0,
        "totalValue": 2291836266.62,
        "pe": 10.81,
        "pbv": 1.11,
        "bookValuePerShare": 3.54,
        "dividendYield": 4.059999942779541,
        "marketCap": 15070500000.0,
        "listedShare": 3825000000.0,
        "par": 1.0,
        "financialDate": "2023-09-30T00:00:00+07:00",
        "turnoverRatio": 15.222754823529412,
        "beta": 0.6,
        "dividendPayoutRatio": 0.44,
        "averageValue": 9431424.965514403
    },
    {
        "date": "2024-02-23T00:00:00+07:00",
        "period": "YTD",
        "symbol": "WHAUP",
        "market": "SET",
        "industry": "RESOURC",
        "sector": "ENERG",
        "prior": 3.94,
        "open": 3.96,
        "high": 4.28,
        "low": 3.9,
        "average": null,
        "close": 4.02,
        "change": 0.07999999999999963,
        "percentChange": 2.0304568527918687,
        "totalVolume": 139292648.0,
        "totalValue": 567058755.2,
        "pe": 11.03,
        "pbv": 1.13,
        "bookValuePerShare": 3.54,
        "dividendYield": 3.9800000190734863,
        "marketCap": 15376500000.0,
        "listedShare": 3825000000.0,
        "par": 1.0,
        "financialDate": "2023-09-30T00:00:00+07:00",
        "turnoverRatio": 3.6416378562091505,
        "beta": 0.66,
        "dividendPayoutRatio": 0.44,
        "averageValue": 14539968.082051283
    }
]